asltk/__init__.py
asltk/asldata.py
asltk/aux_methods.py
asltk/data/__init__.py
asltk/data/brain_atlas/AAL32024.json
asltk/data/brain_atlas/AAT2022.json
asltk/data/brain_atlas/AICHA2021.json
asltk/data/brain_atlas/DKA2006.json
asltk/data/brain_atlas/FCA7N2011.json
asltk/data/brain_atlas/HA2003.json
asltk/data/brain_atlas/HOCSA2006.json
asltk/data/brain_atlas/JHA2005.json
asltk/data/brain_atlas/LGPHCC2022.json
asltk/data/brain_atlas/MNI2009.json
asltk/data/brain_atlas/__init__.py
asltk/data/reports/__init__.py
asltk/data/reports/basic_report.py
asltk/data/reports/parcellation_report.py
asltk/logging_config.py
asltk/models/__init__.py
asltk/models/signal_dynamic.py
asltk/mri_parameters.py
asltk/reconstruction/__init__.py
asltk/reconstruction/cbf_mapping.py
asltk/reconstruction/multi_dw_mapping.py
asltk/reconstruction/multi_te_mapping.py
asltk/reconstruction/t2_mapping.py
asltk/reconstruction/ultralong_te_mapping.py
asltk/registration/__init__.py
asltk/registration/asl_normalization.py
asltk/scripts/cbf.py
asltk/scripts/dw_asl.py
asltk/scripts/generate_subtracted_asl_image.py
asltk/scripts/t2_maps.py
asltk/scripts/te_asl.py
asltk/scripts/ultralong_te_asl.py
asltk/smooth/__init__.py
asltk/smooth/gaussian.py
asltk/smooth/median.py
asltk/utils/__init__.py
asltk/utils/image_manipulation.py
asltk/utils/image_statistics.py
asltk/utils/io.py
asltk-1.0.2.dist-info/LICENSE
asltk-1.0.2.dist-info/METADATA
asltk-1.0.2.dist-info/WHEEL
asltk-1.0.2.dist-info/entry_points.txt
asltk-1.0.2.dist-info/RECORD
