Metadata-Version: 2.3
Name: asltk
Version: 1.0.2
Summary: A quick to use library to process images for MRI Arterial Spin Labeling imaging protocols.
License: MIT
Author: Antonio Senra Filho
Author-email: acsenrafilho@alumni.usp.br
Requires-Python: >=3.10,<4.0
Classifier: Intended Audience :: Healthcare Industry
Classifier: Intended Audience :: Science/Research
Classifier: License :: OSI Approved :: MIT License
Classifier: Operating System :: OS Independent
Classifier: Programming Language :: Python :: 3
Classifier: Programming Language :: Python :: 3.10
Classifier: Programming Language :: Python :: 3.11
Classifier: Programming Language :: Python :: 3.12
Classifier: Programming Language :: Python :: 3.13
Classifier: Topic :: Scientific/Engineering
Classifier: Topic :: Scientific/Engineering :: Image Processing
Classifier: Topic :: Scientific/Engineering :: Medical Science Apps.
Requires-Dist: SimpleITK (>=2.4.0,<3.0.0)
Requires-Dist: antspyx (>=0.6.1,<0.7.0)
Requires-Dist: dill (>=0.3.9,<0.4.0)
Requires-Dist: kagglehub (>=0.3.12,<0.4.0)
Requires-Dist: numpy (>=1.22.4,<2.0.0)
Requires-Dist: pybids (>=0.17.2,<0.18.0)
Requires-Dist: rich (>=13.8.1,<14.0.0)
Requires-Dist: scipy (>=1.13.1,<2.0.0)
Project-URL: Code, https://github.com/LOAMRI/asltk
Project-URL: Code Issues, https://github.com/LOAMRI/asltk/issues
Project-URL: Documentation, https://asltk.readthedocs.io/en/latest
